cubeai/__init__.py
cubeai/cube/__init__.py
cubeai/cube/cube.py
cubeai/solver/__init__.py
cubeai/solver/learning.py
cubeai/solver/search.py
cubeai/solver/solver.py
cubeai/solver/util.py
cubeai-0.0.16.dist-info/METADATA
cubeai-0.0.16.dist-info/RECORD
cubeai-0.0.16.dist-info/WHEEL
cubeai-0.0.16.dist-info/top_level.txt
