Metadata-Version: 2.1
Name: cubeai
Version: 0.0.16
Summary: an AI solver for the Rubik's Cube
Home-page: https://github.cs.huji.ac.il/ransha/ai_project
Author: Ran Shaham
Author-email: ran.shaham1@mail.huji.ac.il
License: UNKNOWN
Platform: UNKNOWN
Classifier: Programming Language :: Python :: 3
Classifier: License :: OSI Approved :: MIT License
Classifier: Operating System :: OS Independent
Requires-Dist: numpy
Requires-Dist: pandas
